README
setup.py
src/cryotec_server/__init__.py
src/cryotec_server/dashboard.py
src/cryotec_server/menu.py
src/cryotec_server/settings.py
src/cryotec_server/urls.py
src/cryotec_server.egg-info/PKG-INFO
src/cryotec_server.egg-info/SOURCES.txt
src/cryotec_server.egg-info/dependency_links.txt
src/cryotec_server.egg-info/requires.txt
src/cryotec_server.egg-info/top_level.txt
src/cryotec_server/actions/__init__.py
src/cryotec_server/actions/admin.py
src/cryotec_server/actions/forms.py
src/cryotec_server/actions/models.py
src/cryotec_server/actions/tests.py
src/cryotec_server/actions/views.py
src/cryotec_server/actions/migrations/0001_initial.py
src/cryotec_server/actions/migrations/0002_auto__add_field_report_reported_by.py
src/cryotec_server/actions/migrations/__init__.py
src/cryotec_server/actiontemplates/__init__.py
src/cryotec_server/actiontemplates/admin.py
src/cryotec_server/actiontemplates/models.py
src/cryotec_server/actiontemplates/tests.py
src/cryotec_server/actiontemplates/views.py
src/cryotec_server/checklists/__init__.py
src/cryotec_server/checklists/admin.py
src/cryotec_server/checklists/forms.py
src/cryotec_server/checklists/models.py
src/cryotec_server/checklists/tests.py
src/cryotec_server/checklists/views.py
src/cryotec_server/clients/__init__.py
src/cryotec_server/clients/admin.py
src/cryotec_server/clients/models.py
src/cryotec_server/clients/tests.py
src/cryotec_server/clients/views.py
src/cryotec_server/clients/migrations/0001_initial.py
src/cryotec_server/clients/migrations/0002_auto__add_field_client_address_machine__add_field_client_address_legal.py
src/cryotec_server/clients/migrations/__init__.py
src/cryotec_server/files/__init__.py
src/cryotec_server/files/admin.py
src/cryotec_server/files/forms.py
src/cryotec_server/files/models.py
src/cryotec_server/files/tests.py
src/cryotec_server/files/views.py
src/cryotec_server/libs/__init__.py
src/cryotec_server/libs/admin.py
src/cryotec_server/libs/modelmixins.py
src/cryotec_server/libs/templatetags/__init__.py
src/cryotec_server/libs/templatetags/cryotec_extras.py
src/cryotec_server/machines/__init__.py
src/cryotec_server/machines/admin.py
src/cryotec_server/machines/models.py
