Metadata-Version: 1.0
Name: cryotec-server
Version: 1.3.4
Summary: Cryotec Service Server
Home-page: http://github.com/darvin/cryotec_server
Author: Sergey Klimov
Author-email: UNKNOWN
License: Greedy Open Source
Platform: UNKNOWN
